Metadata-Version: 1.1
Name: howmanypeoplearearound
Version: 0.4.0
Summary: A tshark wrapper to count the number of cellphones in the vicinity
Home-page: https://github.com/schollz/howmanypeoplearearound
Author: schollz
Author-email: hypercube.platforms@gmail.com
License: UNKNOWN
Download-URL: https://github.com/schollz/howmanypeoplearearound/archive/v0.3.5.tar.gz
Keywords: tshark,wifi,location
Platform: UNKNOWN
